poetichelloworld/PoeticHelloWorld.py
poetichelloworld/__init__.py
poetichelloworld-0.1.0.dist-info/METADATA
poetichelloworld-0.1.0.dist-info/WHEEL
poetichelloworld-0.1.0.dist-info/RECORD
